tornado_async_server/async_server_test.py
tornado_async_server/__init__.py
emulate_tornado_server-1.0.0.dist-info/RECORD
emulate_tornado_server-1.0.0.dist-info/metadata.json
emulate_tornado_server-1.0.0.dist-info/WHEEL
emulate_tornado_server-1.0.0.dist-info/METADATA
emulate_tornado_server-1.0.0.dist-info/top_level.txt
emulate_tornado_server-1.0.0.dist-info/DESCRIPTION.rst
