Metadata-Version: 2.0
Name: emulate-tornado-server
Version: 1.0.0
Summary: Collection of short functions to simplify tornado-based clients testing
Home-page: https://github.com/risboo6909/emulate_tornado_server
Author: Boris Tatarintsev
Author-email: ttyv00@gmail.com
License: MIT
Keywords: tornado testing http server client
Platform: UNKNOWN
Classifier: Development Status :: 3 - Alpha
Classifier: Intended Audience :: Developers
Classifier: License :: OSI Approved :: MIT License
Classifier: Programming Language :: Python :: 2.7
Requires-Dist: tornado
